{
  "simulation_meta_data": {
    "experiment_name": "ABCDE Experiment",
    "model_name": "architecture_model",
    "duration": 10,
    "report": "",
    "datapoints": 50,
    "seed": 979
  },
  "request_generators": [
    {
      "type": "interval",
      "config": {
        "microservice": "frontend",
        "operation": "getCatalog",
        "interval": 2
      }
    },
    {
      "type": "interval",
      "config": {
        "microservice": "frontend",
        "operation": "createBook",
        "interval": 2.5
      }
    },
    {
      "type": "interval",
      "config": {
        "microservice": "frontend",
        "operation": "createUser",
        "interval": 3
      }
    },
    {
      "type": "interval",
      "config": {
        "microservice": "frontend",
        "operation": "getUsers",
        "interval": 4
      }
    }
  ],

  "chaos_monkeys": [
    {
      "type": "monkey",
      "config":     {
        "microservice": "users",
        "instances": 1,
        "time": 6
      }
    }
  ]
}